pathfinder/__init__.py
pathfinder/operators/__init__.py
pathfinder/operators/base.py
pathfinder/operators/get.py
pathfinder/operators/gpo.py
pathfinder/operators/login.py
pathfinder/operators/sub.py
pathfinder/parser.py
pathfinder/telnet.py
axia_pathfinder_client-0.2.5.dist-info/LICENSE
axia_pathfinder_client-0.2.5.dist-info/METADATA
axia_pathfinder_client-0.2.5.dist-info/WHEEL
axia_pathfinder_client-0.2.5.dist-info/RECORD
