Metadata-Version: 2.1
Name: axia-pathfinder-client
Version: 0.2.5
Summary: Proof of concept Axia Pathfinder API/SDK.
License: AGPLv3
Author: RaBe IT-Reaktion
Author-email: it@rabe.ch
Requires-Python: >=3.11,<4.0
Classifier: License :: Other/Proprietary License
Classifier: Programming Language :: Python :: 3
Classifier: Programming Language :: Python :: 3.11
Classifier: Programming Language :: Python :: 3.12
Requires-Dist: parsy (>=2.1,<3.0)
